NightWindGameLib/__init__.py
NightWindGameLib/Arcade/__init__.py
NightWindGameLib/Arcade/car.py
NightWindGameLib/Arcade/covid19.py
NightWindGameLib/Arcade/fish.py
NightWindGameLib/Arcade/hitTheBlock.py
NightWindGameLib/Arcade/__pycache__/__init__.cpython-38.pyc
NightWindGameLib/Arcade/__pycache__/__init__.cpython-39.pyc
NightWindGameLib/Arcade/__pycache__/car.cpython-39.pyc
NightWindGameLib/Arcade/__pycache__/covid19.cpython-39.pyc
NightWindGameLib/Arcade/__pycache__/fish.cpython-39.pyc
NightWindGameLib/Arcade/__pycache__/hitTheBlock.cpython-39.pyc
NightWindGameLib/Arcade/images_car/big_car1.png
NightWindGameLib/Arcade/images_car/big_car2.png
NightWindGameLib/Arcade/images_car/big_car3.png
NightWindGameLib/Arcade/images_car/game_over.png
NightWindGameLib/Arcade/images_car/heal.png
NightWindGameLib/Arcade/images_car/road.png
NightWindGameLib/Arcade/images_car/score.json
NightWindGameLib/Arcade/images_car/small_car1.png
NightWindGameLib/Arcade/images_car/small_car2.png
NightWindGameLib/Arcade/images_car/small_car3.png
NightWindGameLib/Arcade/images_car/small_car4.png
NightWindGameLib/Arcade/images_fish/blue_fish.png
NightWindGameLib/Arcade/images_fish/eat_sound.wav
NightWindGameLib/Arcade/images_fish/game_over.png
NightWindGameLib/Arcade/images_fish/game_over_sound.wav
NightWindGameLib/Arcade/images_fish/game_pause.png
NightWindGameLib/Arcade/images_fish/green_fish.png
NightWindGameLib/Arcade/images_fish/new_sea.png
NightWindGameLib/Arcade/images_fish/newsea.png
NightWindGameLib/Arcade/images_fish/player.png
NightWindGameLib/Arcade/images_fish/purple_fish.png
NightWindGameLib/Arcade/images_fish/red_fish.png
NightWindGameLib/Arcade/images_fish/screenshot.png
NightWindGameLib/Arcade/images_fish/sea.png
NightWindGameLib/Arcade/images_fish/yellow_fish.png
NightWindGameLib/Chess/ConnectFour.py
NightWindGameLib/Chess/Isolation.py
NightWindGameLib/Chess/Isolation.ui
NightWindGameLib/Chess/TicTacToe.py
NightWindGameLib/Chess/__init__.py
NightWindGameLib/Chess/chess.py
NightWindGameLib-0.8.5.dist-info/METADATA
NightWindGameLib-0.8.5.dist-info/WHEEL
NightWindGameLib-0.8.5.dist-info/top_level.txt
NightWindGameLib-0.8.5.dist-info/RECORD
