Metadata-Version: 2.1
Name: NightWindGameLib
Version: 0.8.5
Summary: Some little games
Home-page: https://github.com
Author: Nova_NightWind0311
Author-email: nova_nightwind0311@qq.com
License: UNKNOWN
Platform: UNKNOWN
Classifier: Programming Language :: Python :: 3
Classifier: License :: OSI Approved :: MIT License
Classifier: Operating System :: OS Independent
Requires-Dist: arcade (>=2.5.5)
Requires-Dist: pygame (>=2.0.1)
Requires-Dist: PySide2 (>=5.14)
Requires-Dist: sympy (>=1.7.0)
Requires-Dist: Pillow (>=8.2.0)
